pexels_api/__init__.py
pexels_api/api.py
pexels_api/tools/__init__.py
pexels_api/tools/photo.py
pexels_api-1.0.1.dist-info/LICENSE
pexels_api-1.0.1.dist-info/METADATA
pexels_api-1.0.1.dist-info/WHEEL
pexels_api-1.0.1.dist-info/top_level.txt
pexels_api-1.0.1.dist-info/RECORD
