Metadata-Version: 2.1
Name: pexels-api
Version: 1.0.1
Summary: Use Pexels API v1 with Python
Home-page: https://github.com/AguilarLagunasArturo/pexels-api
Author: Arturo Aguilar Lagunas
Author-email: aguilar.lagunas.arturo@gmail.com
License: UNKNOWN
Keywords: pexels api images photos
Platform: UNKNOWN
Classifier: Programming Language :: Python
Classifier: License :: OSI Approved :: MIT License
Classifier: Operating System :: OS Independent
